pyquots/__init__.py
pyquots/errors.py
pyquots/pyquots.py
pyquots/pyquots_named_tuples.py
pyquots-0.0.1.dist-info/LICENSE
pyquots-0.0.1.dist-info/METADATA
pyquots-0.0.1.dist-info/WHEEL
pyquots-0.0.1.dist-info/top_level.txt
pyquots-0.0.1.dist-info/RECORD
