Metadata-Version: 1.0
Name: pyquots
Version: 0.0.1
Summary: Python client for Quots
Home-page: https://github.com/KinkyDesign/jaqpotpy
Author: Pantelis Karatzas
Author-email: pantelispanka@gmail.com
License: GNU General Public License v3.0
Platform: UNKNOWN
